wagtail_spa_integration/__init__.py
wagtail_spa_integration/apps.py
wagtail_spa_integration/filters.py
wagtail_spa_integration/headless_preview_api.py
wagtail_spa_integration/py.typed
wagtail_spa_integration/serializers.py
wagtail_spa_integration/templates/wagtailadmin/pages/_preview_button_on_edit.html
wagtail_spa_integration/templatetags/__init__.py
wagtail_spa_integration/templatetags/wagtail_spa_integration_tags.py
wagtail_spa_integration/tests.py
wagtail_spa_integration/utils.py
wagtail_spa_integration/views.py
wagtail_spa_integration-3.3.0.dist-info/LICENSE
wagtail_spa_integration-3.3.0.dist-info/METADATA
wagtail_spa_integration-3.3.0.dist-info/WHEEL
wagtail_spa_integration-3.3.0.dist-info/RECORD
